bttc/__init__.py
bttc/apk_utils.py
bttc/ble_data.py
bttc/ble_utils.py
bttc/bt_data.py
bttc/bt_utils.py
bttc/common_data.py
bttc/constants.py
bttc/core.py
bttc/errors.py
bttc/general_data.py
bttc/general_utils.py
bttc/mc_data.py
bttc/mc_utils.py
bttc/strategy.py
bttc/utils_loader.py
bttc/wifi_utils.py
bttc/cli/__init__.py
bttc/cli/constants.py
bttc/cli/main.py
bttc/mobly_android_device_lib/jsonrpc_client_base.py
bttc/mobly_android_device_lib/tl4a_snippet_client.py
bttc/mobly_android_device_lib/services/sl4a_client.py
bttc/mobly_android_device_lib/services/sl4a_service.py
bttc/profiles/a2dp/a2dp_strategy.py
bttc/profiles/avrcp/__init_.py
bttc/profiles/avrcp/__init__.py
bttc/profiles/avrcp/avrcp_facade.py
bttc/profiles/avrcp/avrcp_target_devices.py
bttc/profiles/avrcp/errors.py
bttc/profiles/hfp/__init__.py
bttc/profiles/hfp/constants.py
bttc/profiles/hfp/errors.py
bttc/profiles/hfp/hfp_data.py
bttc/profiles/hfp/hfp_devices.py
bttc/profiles/hfp/hfp_facade.py
bttc/profiles/hfp/hfp_strategy.py
bttc/utils/__init__.py
bttc/utils/ad_checker.py
bttc/utils/bds_broker.py
bttc/utils/device_factory.py
bttc/utils/dialer_simulator.py
bttc/utils/key_events_handler.py
bttc/utils/log_parser.py
bttc/utils/logcat.py
bttc/utils/pixellogger_utils.py
bttc/utils/retry.py
bttc/utils/typing_utils.py
bttc/utils/bt/connection_factory.py
bttc/utils/bt/strategy.py
bttc/utils/iperf/__init__.py
bttc/utils/iperf/errors.py
bttc/utils/media_player/media_player_agent_facade.py
bttc/utils/media_player/yt_player_agent.py
bttc/utils/ui_pages/__init__.py
bttc/utils/ui_pages/errors.py
bttc/utils/ui_pages/ui_core.py
bttc/utils/ui_pages/ui_node.py
bttc/utils/ui_pages/utils.py
bttc/utils/ui_pages/system/__init__.py
bttc/utils/ui_pages/system/constants.py
bttc-0.0.88.dist-info/LICENSE
bttc-0.0.88.dist-info/METADATA
bttc-0.0.88.dist-info/WHEEL
bttc-0.0.88.dist-info/top_level.txt
bttc-0.0.88.dist-info/RECORD
