Metadata-Version: 2.1
Name: bttc
Version: 0.0.88
Summary: A package to provide common utilities for BT testing.
Home-page: https://github.com/johnklee/bt_test_common
Author: John Lee/Yuan Long Luo/Denny Chai
Author-email: puremonkey2007@gmail.com
License: MIT License
Classifier: Development Status :: 1 - Planning
Classifier: Intended Audience :: Science/Research
Classifier: License :: OSI Approved :: MIT License
Classifier: Operating System :: POSIX :: Linux
Classifier: Programming Language :: Python :: 3.8
Classifier: Programming Language :: Python :: 3.9
Classifier: Programming Language :: Python :: 3.10
Classifier: Programming Language :: Python :: 3.11
License-File: LICENSE
Requires-Dist: PyYAML (==6.0.1)
Requires-Dist: cmd2 (==2.4.3)
Requires-Dist: deprecation (==2.1.0)
Requires-Dist: mobly (>=1.12.2)
Requires-Dist: numpy
Requires-Dist: portpicker (==1.6.0)
Requires-Dist: psutil (==5.9.8)
Requires-Dist: pure-python-adb (==0.3.0.dev0)
Requires-Dist: python-dotenv (==1.0.1)
Requires-Dist: six (==1.16.0)
Requires-Dist: snippet-uiautomator (>=1.1.0)
